pk_dogsApi
