Metadata-Version: 2.1
Name: pk-dogsApi
Version: 0.0.3
Summary: Extrae un listado de razas de perros de la Api Publica de Dogs
Home-page: https://github.com/AntoGzz/
Author: AntoGzz
Author-email: quirozd70@gmail.com
License: MIT
Platform: UNKNOWN
Classifier: Development Status :: 3 - Alpha
Classifier: Intended Audience :: Developers
Classifier: Topic :: Software Development :: Build Tools
Classifier: License :: OSI Approved :: MIT License
Classifier: Programming Language :: Python :: 3
